setup.py
vencryption/__init__.py
vencryption/encryption.py
vencryption2.egg-info/PKG-INFO
vencryption2.egg-info/SOURCES.txt
vencryption2.egg-info/dependency_links.txt
vencryption2.egg-info/requires.txt
vencryption2.egg-info/top_level.txt
vencryption/znorg/__init__.py